mpex_probabilities/Binomialdistribution.py
mpex_probabilities/Gaussiandistribution.py
mpex_probabilities/Generaldistribution.py
mpex_probabilities/__init__.py
mpex_probabilities-0.2.dist-info/METADATA
mpex_probabilities-0.2.dist-info/WHEEL
mpex_probabilities-0.2.dist-info/top_level.txt
mpex_probabilities-0.2.dist-info/RECORD
