Metadata-Version: 2.1
Name: mpex-probabilities
Version: 0.2
Summary: mpex distributions
Home-page: UNKNOWN
Author: UNKNOWN
Author-email: UNKNOWN
License: UNKNOWN
Platform: UNKNOWN
